rpadx/__init__.py
rpadx/logger.py
rpadx/slack.py
rpadx/google/__init__.py
rpadx/google/app_script_api.py
rpadx/google/auth.py
rpadx/google/docs_api.py
rpadx/google/drive_api.py
rpadx/google/sheets_api.py
caad_rpa-1.0.2.dist-info/METADATA
caad_rpa-1.0.2.dist-info/WHEEL
caad_rpa-1.0.2.dist-info/top_level.txt
caad_rpa-1.0.2.dist-info/RECORD
