Metadata-Version: 2.1
Name: caad-rpa
Version: 1.0.2
Summary: RPAライブラリ
Author: odxチーム
Author-email: caad_odx_team@ca-adv.co.jp
Classifier: Programming Language :: Python :: 3.7
Classifier: Programming Language :: Python :: 3.8
Classifier: Programming Language :: Python :: 3.9
Classifier: Programming Language :: Python :: 3.10
Requires-Dist: requests (~=2.31.0)
Requires-Dist: google-auth-oauthlib (~=0.7.1)
Requires-Dist: google-api-python-client (~=2.69.0)
Requires-Dist: pandas (~=2.1.3)
Requires-Dist: setuptools (~=65.5.0)
